pjrmi/__init__.py
pjrmi/_config.py
pjrmi/_util.py
pjrmi/lib/pjrmi.jar
pjrmi-1.13.17.dist-info/METADATA
pjrmi-1.13.17.dist-info/WHEEL
pjrmi-1.13.17.dist-info/RECORD
